pytest_params/__init__.py
pytest_params/params.py
pytest_params/request_params.py
pytest_params-0.2.0.dist-info/LICENSE
pytest_params-0.2.0.dist-info/WHEEL
pytest_params-0.2.0.dist-info/METADATA
pytest_params-0.2.0.dist-info/RECORD
