Metadata-Version: 2.1
Name: pytest-params
Version: 0.2.0
Summary: Simplified pytest test case parameters.
Author: Joao Coelho
Classifier: License :: OSI Approved :: MIT License
Classifier: Framework :: Pytest
Requires-Dist: pytest>=7.0.0
Project-URL: Home, https://github.com/joaonc/pytest-params
